druid_libs/__init__.py
druid_libs/tests_tools/__init__.py
druid_libs/tests_tools/fake_event.py
druid_libs/tests_tools/lambda_module.py
druid_libs-0.1.15.dist-info/LICENSE
druid_libs-0.1.15.dist-info/WHEEL
druid_libs-0.1.15.dist-info/METADATA
druid_libs-0.1.15.dist-info/RECORD
