Metadata-Version: 2.1
Name: druid-libs
Version: 0.1.15
Summary: Python utilities for Druid projects
Home-page: https://github.com/jasonFerre/python-lib
License: MIT
Keywords: Poetry,Virtual Environments,Tutorial,Packages,Packaging,Druid
Author: Druid
Maintainer: Geyson
Maintainer-email: geyson.ferreira@druid.com
Requires-Python: >=3.7,<4.0
Classifier: License :: OSI Approved :: MIT License
Classifier: Programming Language :: Python :: 3
Classifier: Programming Language :: Python :: 3.7
Classifier: Programming Language :: Python :: 3.8
Classifier: Programming Language :: Python :: 3.9
Project-URL: Documentation, https://github.com/jasonFerre/python-lib
Project-URL: Repository, https://github.com/jasonFerre/python-lib.git
